pycuda/_pvt_struct.cpython-311-x86_64-linux-gnu.so
pycuda/reduction.py
pycuda/compiler.py
pycuda/_mymako.py
pycuda/autoprimaryctx.py
pycuda/debug.py
pycuda/_driver.cpython-311-x86_64-linux-gnu.so
pycuda/curandom.py
pycuda/cumath.py
pycuda/gpuarray.py
pycuda/autoinit.py
pycuda/_cluda.py
pycuda/__init__.py
pycuda/tools.py
pycuda/characterize.py
pycuda/driver.py
pycuda/scan.py
pycuda/elementwise.py
pycuda/gl/autoinit.py
pycuda/gl/__init__.py
pycuda/cuda/pycuda-helpers.hpp
pycuda/cuda/pycuda-complex-impl.hpp
pycuda/cuda/pycuda-complex.hpp
pycuda/compyte/dtypes.py
pycuda/compyte/__init__.py
pycuda/compyte/array.py
pycuda/sparse/packeted.py
pycuda/sparse/pkt_build_cython.pyx
pycuda/sparse/inner.py
pycuda/sparse/operator.py
pycuda/sparse/cg.py
pycuda/sparse/pkt_build.py
pycuda/sparse/coordinate.py
pycuda/sparse/__init__.py
pycuda_gml-2024.1.2.dist-info/LICENSE
pycuda_gml-2024.1.2.dist-info/RECORD
pycuda_gml-2024.1.2.dist-info/METADATA
pycuda_gml-2024.1.2.dist-info/WHEEL
pycuda_gml-2024.1.2.dist-info/top_level.txt
