Metadata-Version: 2.1
Name: pycuda-gml
Version: 2024.1.2
Summary: Python wrapper for Nvidia CUDA
Home-page: http://mathema.tician.de/software/pycuda
Author: Andreas Kloeckner
Author-email: inform@tiker.net
License: MIT
Project-URL: Source, https://github.com/inducer/pycuda
Classifier: Environment :: Console
Classifier: Development Status :: 5 - Production/Stable
Classifier: Intended Audience :: Developers
Classifier: Intended Audience :: Other Audience
Classifier: Intended Audience :: Science/Research
Classifier: License :: OSI Approved :: MIT License
Classifier: Natural Language :: English
Classifier: Programming Language :: C++
Classifier: Programming Language :: Python
Classifier: Programming Language :: Python :: 3
Classifier: Topic :: Scientific/Engineering
Classifier: Topic :: Scientific/Engineering :: Mathematics
Classifier: Topic :: Scientific/Engineering :: Physics
Classifier: Topic :: Scientific/Engineering :: Visualization
Requires-Python: ~=3.8
License-File: LICENSE
Requires-Dist: pytools>=2011.2
Requires-Dist: platformdirs>=2.2.0
Requires-Dist: mako
